odoo/addons/so_group_stock_user_read/README.rst
odoo/addons/so_group_stock_user_read/__init__.py
odoo/addons/so_group_stock_user_read/__manifest__.py
odoo/addons/so_group_stock_user_read/i18n/es.po
odoo/addons/so_group_stock_user_read/security/so_group_stock_user_read_security.xml
odoo/addons/so_group_stock_user_read/static/description/icon.png
odoo/addons/so_group_stock_user_read/views/product_views.xml
odoo/addons/so_group_stock_user_read/views/sale_order_views.xml
odoo_addon_so_group_stock_user_read-16.0.1.0.1.2.dist-info/METADATA
odoo_addon_so_group_stock_user_read-16.0.1.0.1.2.dist-info/WHEEL
odoo_addon_so_group_stock_user_read-16.0.1.0.1.2.dist-info/top_level.txt
odoo_addon_so_group_stock_user_read-16.0.1.0.1.2.dist-info/RECORD
