Metadata-Version: 2.1
Name: odoo-addon-so_group_stock_user_read
Version: 16.0.1.0.1.2
Requires-Python: >=3.10
Requires-Dist: odoo>=16.0a,<16.1dev
Summary: Sale Order Group Stock User Read
Home-page: https://github.com/sygel-technology/sy-sale-workflow
License: AGPL-3
Author: Sygel, Odoo Community Association (OCA)
Author-email: support@odoo-community.org
Classifier: Programming Language :: Python
Classifier: Framework :: Odoo
Classifier: Framework :: Odoo :: 16.0
Classifier: License :: OSI Approved :: GNU Affero General Public License v3
